setup.py
ppski_distributions/Binomialdistribution.py
ppski_distributions/Gaussiandistribution.py
ppski_distributions/Generaldistribution.py
ppski_distributions/__init__.py
ppski_distributions.egg-info/PKG-INFO
ppski_distributions.egg-info/SOURCES.txt
ppski_distributions.egg-info/dependency_links.txt
ppski_distributions.egg-info/not-zip-safe
ppski_distributions.egg-info/top_level.txt