Metadata-Version: 2.1
Name: ppski-distributions
Version: 0.2
Summary: Gaussian and Binomial distributions
Home-page: UNKNOWN
Author: Paula Pawlowski
Author-email: paula.pwski@gmail.com
License: UNKNOWN
Platform: UNKNOWN
